odoo/addons/odoo_custom_server/__init__.py
odoo/addons/odoo_custom_server/__manifest__.py
odoo/addons/odoo_custom_server/command_server.py
odoo/addons/odoo_custom_server/cli/__init__.py
odoo/addons/odoo_custom_server/cli/generic_server.py
odoo/addons/odoo_custom_server/cli/update_server.py
odoo/addons/odoo_custom_server/cli/web_server.py
odoo/addons/odoo_custom_server/odoo_patch/__init__.py
odoo/addons/odoo_custom_server/odoo_patch/sql_db.py
mangono_addon_odoo_custom_server-1.2.0.dist-info/METADATA
mangono_addon_odoo_custom_server-1.2.0.dist-info/WHEEL
mangono_addon_odoo_custom_server-1.2.0.dist-info/entry_points.txt
mangono_addon_odoo_custom_server-1.2.0.dist-info/top_level.txt
mangono_addon_odoo_custom_server-1.2.0.dist-info/RECORD
